pytorch_template/__init__.py
pytorch_template/datasets/__init__.py
pytorch_template/datasets/mnist.py
pytorch_template/metrics/__init__.py
pytorch_template/metrics/accuracy.py
pytorch_template/metrics/average.py
pytorch_template/models/__init__.py
pytorch_template/models/lenet.py
pytorch_template/optim.py
pytorch_template/trainers/__init__.py
pytorch_template/trainers/trainer.py
pytorch_template/utils/__init__.py
pytorch_template/utils/conf.py
pytorch_template/utils/utils.py
pytorch_template-0.1.0.dist-info/WHEEL
pytorch_template-0.1.0.dist-info/METADATA
pytorch_template-0.1.0.dist-info/RECORD
