Metadata-Version: 2.1
Name: pytorch-template
Version: 0.1.0
Summary: 
Author: なるみ
Author-email: toucans-cutouts0f@icloud.com
Requires-Python: >=3.8,<4.0
Classifier: Programming Language :: Python :: 3
Classifier: Programming Language :: Python :: 3.8
Classifier: Programming Language :: Python :: 3.9
Classifier: Programming Language :: Python :: 3.10
Classifier: Programming Language :: Python :: 3.11
Requires-Dist: loguru (>=0.6.0,<0.7.0)
Requires-Dist: mlflow (>=1.30.0,<2.0.0)
Requires-Dist: omegaconf (>=2.2.3,<3.0.0)
Requires-Dist: torch (>=1.12.1,<2.0.0)
Requires-Dist: torchvision (>=0.13.1,<0.14.0)
Requires-Dist: tqdm (>=4.64.1,<5.0.0)
